pyclimproj/__init__.py
pyclimproj/downloader.py
pyclimproj/tests/__init__.py
pyclimproj/tests/test_downloader.py
pyclimproj-2025.5.30.dist-info/LICENSE
pyclimproj-2025.5.30.dist-info/METADATA
pyclimproj-2025.5.30.dist-info/WHEEL
pyclimproj-2025.5.30.dist-info/top_level.txt
pyclimproj-2025.5.30.dist-info/RECORD
