Metadata-Version: 2.1
Name: pyclimproj
Version: 2025.5.30
Summary: A simple climate projection downloader for ORNL Hydro9505 data
Author-email: Surabhi Upadhyay <surabhiupadhyay7@gmail.com>
License: MIT
Project-URL: Homepage, https://github.com/surabhiupadhyay/pyclimproj
Requires-Python: >=3.8
License-File: LICENSE
Requires-Dist: requests
Requires-Dist: beautifulsoup4
Requires-Dist: tqdm
